Metadata-Version: 1.0
Name: superprompt
Version: 1.2.0
Summary: Prompting on steroids
Home-page: https://github.com/ddorn/superprompt
Author: Diego Dorn
Author-email: diego.dorn@free.fr
License: MIT
Platform: UNKNOWN
